example_kishor/addTwoNumbers.py
Example_kishor-1.0.0.dist-info/LICENSE
Example_kishor-1.0.0.dist-info/METADATA
Example_kishor-1.0.0.dist-info/WHEEL
Example_kishor-1.0.0.dist-info/entry_points.txt
Example_kishor-1.0.0.dist-info/top_level.txt
Example_kishor-1.0.0.dist-info/RECORD
